{
    "Big O Freeroll [10 Chips]": [
        {
            "playerName": "grumpyPants",
            "position": 1,
            "chips": 40468
        },
        {
            "playerName": "Furko",
            "position": 2,
            "chips": 15271
        },
        {
            "playerName": "sebpz",
            "position": 3,
            "chips": 1861
        },
        {
            "playerName": "Senility",
            "position": 4,
            "chips": 0
        },
        {
            "playerName": "queeney",
            "position": 5,
            "chips": 0
        },
        {
            "playerName": "rmmvek",
            "position": 6,
            "chips": 0
        },
        {
            "playerName": "iChekRaYs",
            "position": 7,
            "chips": 0
        },
        {
            "playerName": "ArashGh66",
            "position": 8,
            "chips": 0
        },
        {
            "playerName": "weszzzz",
            "position": 9,
            "chips": 0
        },
        {
            "playerName": "Sazxiooo",
            "position": 10,
            "chips": 0
        },
        {
            "playerName": "DerpDoge",
            "position": 11,
            "chips": 0
        },
        {
            "playerName": "sico180350",
            "position": 12,
            "chips": 0
        },
        {
            "playerName": "junglestyle",
            "position": 13,
            "chips": 0
        },
        {
            "playerName": "KSA88",
            "position": 14,
            "chips": 0
        },
        {
            "playerName": "BlackMoon",
            "position": 15,
            "chips": 0
        },
        {
            "playerName": "bottomfeeder",
            "position": 16,
            "chips": 0
        },
        {
            "playerName": "budgreen",
            "position": 17,
            "chips": 0
        },
        {
            "playerName": "VaSa110",
            "position": 18,
            "chips": 0
        },
        {
            "playerName": "pescacidal",
            "position": 19,
            "chips": 0
        },
        {
            "playerName": "Saltlife",
            "position": 20,
            "chips": 0
        },
        {
            "playerName": "Pert",
            "position": 21,
            "chips": 0
        },
        {
            "playerName": "Aether",
            "position": 22,
            "chips": 0
        },
        {
            "playerName": "AC_Sam",
            "position": 23,
            "chips": 0
        },
        {
            "playerName": "Dragnea",
            "position": 24,
            "chips": 0
        },
        {
            "playerName": "Jofu1224",
            "position": 25,
            "chips": 0
        },
        {
            "playerName": "iwetmyplants",
            "position": 26,
            "chips": 0
        },
        {
            "playerName": "joeyjim7",
            "position": 27,
            "chips": 0
        },
        {
            "playerName": "BWA87",
            "position": 28,
            "chips": 0
        },
        {
            "playerName": "cscsabat",
            "position": 29,
            "chips": 0
        },
        {
            "playerName": "carola1006",
            "position": 30,
            "chips": 0
        },
        {
            "playerName": "hgbrd23",
            "position": 31,
            "chips": 0
        },
        {
            "playerName": "xxaress",
            "position": 32,
            "chips": 0
        },
        {
            "playerName": "Pokenstar",
            "position": 33,
            "chips": 0
        },
        {
            "playerName": "Bailey",
            "position": 34,
            "chips": 0
        },
        {
            "playerName": "azarado666",
            "position": 35,
            "chips": 0
        },
        {
            "playerName": "AngelLove",
            "position": 36,
            "chips": 0
        },
        {
            "playerName": "motor1",
            "position": 37,
            "chips": 0
        },
        {
            "playerName": "King66",
            "position": 38,
            "chips": 0
        },
        {
            "playerName": "salo53",
            "position": 39,
            "chips": 0
        },
        {
            "playerName": "clekee415",
            "position": 40,
            "chips": 0
        },
        {
            "playerName": "Madiaz77",
            "position": 41,
            "chips": 0
        },
        {
            "playerName": "NotDragon",
            "position": 42,
            "chips": 0
        },
        {
            "playerName": "timote77",
            "position": 43,
            "chips": 0
        },
        {
            "playerName": "StueyU2",
            "position": 44,
            "chips": 0
        },
        {
            "playerName": "TheHive",
            "position": 45,
            "chips": 0
        },
        {
            "playerName": "igo1960",
            "position": 46,
            "chips": 0
        },
        {
            "playerName": "adnan2909",
            "position": 47,
            "chips": 0
        },
        {
            "playerName": "Charli3m1",
            "position": 48,
            "chips": 0
        }
    ],
    "Badeucy Freeroll [10 Chips]": [
        {
            "playerName": "Code404",
            "position": 1,
            "chips": 4792
        },
        {
            "playerName": "Korpster",
            "position": 2,
            "chips": 3584
        },
        {
            "playerName": "gmab369",
            "position": 3,
            "chips": 2366
        },
        {
            "playerName": "Jeflincx",
            "position": 4,
            "chips": 2165
        },
        {
            "playerName": "Jofu1224",
            "position": 5,
            "chips": 2085
        },
        {
            "playerName": "azarado666",
            "position": 6,
            "chips": 1686
        },
        {
            "playerName": "cscsabat",
            "position": 7,
            "chips": 1524
        },
        {
            "playerName": "arden",
            "position": 8,
            "chips": 1441
        },
        {
            "playerName": "clekee415",
            "position": 9,
            "chips": 1401
        },
        {
            "playerName": "pyper88",
            "position": 10,
            "chips": 1111
        },
        {
            "playerName": "Tonrus",
            "position": 11,
            "chips": 1108
        },
        {
            "playerName": "igo1960",
            "position": 12,
            "chips": 1082
        },
        {
            "playerName": "Shwabra",
            "position": 13,
            "chips": 1025
        },
        {
            "playerName": "8al7i",
            "position": 14,
            "chips": 979
        },
        {
            "playerName": "Antoni",
            "position": 15,
            "chips": 795
        },
        {
            "playerName": "SamSpade01",
            "position": 16,
            "chips": 714
        },
        {
            "playerName": "AprilReigns",
            "position": 16,
            "chips": 714
        },
        {
            "playerName": "rmmvek",
            "position": 18,
            "chips": 619
        },
        {
            "playerName": "xxaress",
            "position": 19,
            "chips": 535
        },
        {
            "playerName": "iChekRaYs",
            "position": 20,
            "chips": 492
        },
        {
            "playerName": "toiletman420",
            "position": 21,
            "chips": 373
        },
        {
            "playerName": "Senility",
            "position": 22,
            "chips": 266
        },
        {
            "playerName": "DeusX",
            "position": 23,
            "chips": 229
        },
        {
            "playerName": "carola1006",
            "position": 24,
            "chips": 101
        },
        {
            "playerName": "Charli3m1",
            "position": 25,
            "chips": 13
        },
        {
            "playerName": "TheHive",
            "position": 26,
            "chips": 0
        },
        {
            "playerName": "AC_Sam",
            "position": 27,
            "chips": 0
        },
        {
            "playerName": "sebpz",
            "position": 28,
            "chips": 0
        },
        {
            "playerName": "motor1",
            "position": 29,
            "chips": 0
        },
        {
            "playerName": "OriirO",
            "position": 30,
            "chips": 0
        },
        {
            "playerName": "Pokenstar",
            "position": 31,
            "chips": 0
        },
        {
            "playerName": "King66",
            "position": 32,
            "chips": 0
        },
        {
            "playerName": "slawdawg420",
            "position": 33,
            "chips": 0
        },
        {
            "playerName": "Pert",
            "position": 34,
            "chips": 0
        },
        {
            "playerName": "JohnnyPoker",
            "position": 35,
            "chips": 0
        },
        {
            "playerName": "kellenwolf",
            "position": 36,
            "chips": 0
        },
        {
            "playerName": "Raptor_",
            "position": 37,
            "chips": 0
        },
        {
            "playerName": "maltay",
            "position": 38,
            "chips": 0
        },
        {
            "playerName": "sooperhandz",
            "position": 39,
            "chips": 0
        }
    ]
}